{
"figPadX": 8.0,
"figPadY": 8.0,
"compPadX": 4.0,
"compPadY": 4.0,
"compFont": {"font": "Serif", "weight": "BOLD", "size":11},
"compAlignment": ["Top", "Left"],
"boxTickness": 1.0,
"boxFillColor": [1.0, 1.0, 1.0],
"boxWidthPolicy": {"type": "BoxSigNamePad", "pad": 20.0},
"boxBorderPad": 4.0,
"sigPadX": 4.0,
"sigPadY": 4.0,
"sigFont": {"font": "Serif", "weight": "BOLD", "size":10},
"descPadX": 4.0,
"groupPadY": 10.0,
"groupPolicy": {"type": "SimplePolicy"},
"arrowLength": 30.0,
"arrowPadX": 2.0,
"arrowThickness": 2.0,
"arrowTipSize": 3.0,
"arrowStyle": "StyleEmpty",
"outputType": "SVGTypeOutput",
"removeDefaultInputArg": true
}
